AUTHORS
ChangeLog
Readme.rst
setup.cfg
setup.py
RMS.egg-info/PKG-INFO
RMS.egg-info/SOURCES.txt
RMS.egg-info/dependency_links.txt
RMS.egg-info/not-zip-safe
RMS.egg-info/pbr.json
RMS.egg-info/top_level.txt
rms/__init__.py
rms/__main__.py