Metadata-Version: 1.0
Name: RMS
Version: 0.0.0
Summary: UNKNOWN
Home-page: UNKNOWN
Author: David Francos Cuartero
Author-email: UNKNOWN
License: UNKNOWN
Platform: UNKNOWN
